basestego/__init__.py
basestego-1.1a0.dist-info/LICENSE
basestego-1.1a0.dist-info/METADATA
basestego-1.1a0.dist-info/WHEEL
basestego-1.1a0.dist-info/top_level.txt
basestego-1.1a0.dist-info/RECORD
