Metadata-Version: 2.1
Name: basestego
Version: 1.1a0
Summary: Steganography with base64
Home-page: UNKNOWN
Author: Sergey Belousov
Author-email: bijereg@gmail.com
License: UNKNOWN
Platform: UNKNOWN
Requires-Python: >=3.6
